COPYING
MANIFEST.in
README.rst
buildout.cfg
develop.cfg
requirements.txt
setup.py
test-requirements.txt
version.txt
bob/__init__.py
bob.pad.voice.egg-info/PKG-INFO
bob.pad.voice.egg-info/SOURCES.txt
bob.pad.voice.egg-info/dependency_links.txt
bob.pad.voice.egg-info/entry_points.txt
bob.pad.voice.egg-info/requires.txt
bob.pad.voice.egg-info/top_level.txt
bob/pad/__init__.py
bob/pad/voice/__init__.py
bob/pad/voice/algorithm/GMM.py
bob/pad/voice/algorithm/HistDistance.py
bob/pad/voice/algorithm/LogRegr.py
bob/pad/voice/algorithm/TensorflowEval.py
bob/pad/voice/algorithm/__init__.py
bob/pad/voice/algorithm/dummy.py
bob/pad/voice/config/__init__.py
bob/pad/voice/config/algorithm/NormLogRegr.py
bob/pad/voice/config/algorithm/PCALogRegr.py
bob/pad/voice/config/algorithm/__init__.py
bob/pad/voice/config/algorithm/gmm_scfc.py
bob/pad/voice/config/algorithm/tensorfloweval.py
bob/pad/voice/config/database/__init__.py
bob/pad/voice/config/database/asvspoof.py
bob/pad/voice/config/database/asvspoof2017.py
bob/pad/voice/config/database/avspoof.py
bob/pad/voice/config/database/voicepa.py
bob/pad/voice/config/extractor/__init__.py
bob/pad/voice/config/extractor/lbp_eurecom.py
bob/pad/voice/config/extractor/lbp_regular8_2hist.py
bob/pad/voice/config/extractor/ratio20.py
bob/pad/voice/config/grid/__init__.py
bob/pad/voice/config/grid/demanding.py
bob/pad/voice/config/preprocessor/__init__.py
bob/pad/voice/database/__init__.py
bob/pad/voice/database/asvspoof.py
bob/pad/voice/database/asvspoof2017.py
bob/pad/voice/database/avspoof.py
bob/pad/voice/database/database.py
bob/pad/voice/database/voicepa.py
bob/pad/voice/extractor/__init__.py
bob/pad/voice/extractor/audio_tensorflow.py
bob/pad/voice/extractor/dummy_tensorflow.py
bob/pad/voice/extractor/glcms.py
bob/pad/voice/extractor/lbp_histograms.py
bob/pad/voice/extractor/lbps.py
bob/pad/voice/extractor/ratios.py
bob/pad/voice/extractor/spectrogram_extended.py
bob/pad/voice/extractor/vectors_ratios.py
bob/pad/voice/test/__init__.py
bob/pad/voice/test/test_databases.py
bob/pad/voice/test/test_spoofspeech.py
bob/pad/voice/test/data/attack_laptop_sentence01.wav
bob/pad/voice/test/data/attack_phone_sentence01.wav
