Metadata-Version: 1.1
Name: bob.pad.voice
Version: 1.0.10
Summary: Package extends bob.pad.base for attack detection in speech
Home-page: https://gitlab.idiap.ch/bob/bob.pad.voice
Author: Pavel Korshunov
Author-email: <pavel.korshunov@idiap.ch>
License: GPLv3
Keywords: presentation attack detection,voice biometrics,framework
Platform: UNKNOWN
Classifier: Framework :: Bob
Classifier: Development Status :: 3 - Alpha
Classifier: Intended Audience :: Developers
Classifier: License :: OSI Approved :: GNU General Public License v3 (GPLv3)
Classifier: Natural Language :: English
Classifier: Programming Language :: Python
Classifier: Topic :: Scientific/Engineering :: Artificial Intelligence
